sparkflow/core/AppManager.py
sparkflow/core/ConfigParser.py
sparkflow/core/DataLineageVisualizer.py
sparkflow/core/QueryBuilder.py
sparkflow/core/SparkManager.py
sparkflow/logging_conf.py
sparkflow/schemas/ConfigSchema.py
sparkflow/schemas/Enum.py
sparkflow/schemas/QuerySchema.py
pyspark_flow-0.1.2.dist-info/LICENSE
pyspark_flow-0.1.2.dist-info/METADATA
pyspark_flow-0.1.2.dist-info/WHEEL
pyspark_flow-0.1.2.dist-info/RECORD
